{"tabs":[{"id":"7370048c-55c8-450f-ae08-072c9a8b5fd6","pane":"main","path":"F:\\Adc\\adc2-audio\\config.xml","type":"projectSettings","mode":"form"},{"id":"6c9ff91d-8d04-4225-b70c-758b94699c40","pane":"main","path":"F:\\Adc\\adc2-audio\\demo\\index.html","type":"file"},{"id":"8b7af32e-4d8e-43fb-9fd0-9c8751e09b3a","pane":"main","path":"F:\\Adc\\adc2-audio\\resources\\dynamic\\default.html","type":"file"},{"id":"7ae59704-5bfb-40ac-abf5-a70aa153e71a","pane":"main","path":"F:\\Adc\\adc2-audio\\resources\\dynamic\\Initializer.js","type":"file"},{"id":"a7f10199-08cd-405b-9dcf-e533fdba9422","pane":"main","path":"F:\\Adc\\adc2-audio\\resources\\dynamic\\styles.css","type":"file"},{"id":"204bae26-be73-47a5-bbc9-bcad0ebe04e3","pane":"main","current":true,"path":"F:\\Adc\\adc2-audio\\resources\\static\\adc-audio.js","type":"file"},{"id":"94c8ab61-555f-425b-b12e-c352c922ae0a","pane":"main","path":"F:\\Adc\\audio\\config.xml","type":"projectSettings","mode":"code","adxVersion":"2.0.0","adxType":"adc"},{"id":"4b14d894-9c15-4fc2-a7c4-18580bf10bc5","pane":"main","path":"F:\\Adc\\audio\\readme.md","type":"file"},{"id":"361d8300-6a55-47f2-9bec-d76d7644eb64","pane":"main","path":"F:\\Adc\\audio\\changelog.md","type":"file"}]}